setup.cfg
setup.py
elb_rotate_certs/RotateCerts.py
elb_rotate_certs/__init__.py
elb_rotate_certs/cli.py
elb_rotate_certs/util.py
elb_rotate_certs.egg-info/PKG-INFO
elb_rotate_certs.egg-info/SOURCES.txt
elb_rotate_certs.egg-info/dependency_links.txt
elb_rotate_certs.egg-info/entry_points.txt
elb_rotate_certs.egg-info/requires.txt
elb_rotate_certs.egg-info/top_level.txt