Metadata-Version: 1.1
Name: elb-rotate-certs
Version: 0.0.1
Summary: ELB Certificate Rotation Tool
Home-page: https://github.com/WrathOfChris/elb-rotate-certs
Author: Chris Maxwell
Author-email: chris@wrathofchris.com
License: Apache
Download-URL: https://github.com/WrathOfChris/elb-rotate-certs/tarball/0.0.1
Platform: UNKNOWN
